neopyter/__init__.py
neopyter/_version.py
neopyter/handler.py
neopyter/msgpack_queue.py
neopyter/tcp_server.py
neopyter/tests/__init__.py
neopyter/tests/server/test_handlers.py
neopyter-0.3.2.data/data/etc/jupyter/jupyter_server_config.d/neopyter.json
neopyter-0.3.2.data/data/share/jupyter/labextensions/neopyter/package.json
neopyter-0.3.2.data/data/share/jupyter/labextensions/neopyter/schemas/neopyter/labplugin.json
neopyter-0.3.2.data/data/share/jupyter/labextensions/neopyter/schemas/neopyter/neoconf.json
neopyter-0.3.2.data/data/share/jupyter/labextensions/neopyter/schemas/neopyter/package.json.orig
neopyter-0.3.2.data/data/share/jupyter/labextensions/neopyter/static/140.52784a3552c4b644b098.js
neopyter-0.3.2.data/data/share/jupyter/labextensions/neopyter/static/16.20bf3323b6d9e486402f.js
neopyter-0.3.2.data/data/share/jupyter/labextensions/neopyter/static/16.20bf3323b6d9e486402f.js.LICENSE.txt
neopyter-0.3.2.data/data/share/jupyter/labextensions/neopyter/static/186.7997d5a837fbac76ce51.js
neopyter-0.3.2.data/data/share/jupyter/labextensions/neopyter/static/246.c330efe36774e06d8be4.js
neopyter-0.3.2.data/data/share/jupyter/labextensions/neopyter/static/246.c330efe36774e06d8be4.js.LICENSE.txt
neopyter-0.3.2.data/data/share/jupyter/labextensions/neopyter/static/27.34431e507f65995ee0ac.js
neopyter-0.3.2.data/data/share/jupyter/labextensions/neopyter/static/304.e7adbd1dc64a4f150647.js
neopyter-0.3.2.data/data/share/jupyter/labextensions/neopyter/static/330.59a99b8bc80addc9acee.js
neopyter-0.3.2.data/data/share/jupyter/labextensions/neopyter/static/514.9ecfbc06ec3a6698fd1d.js
neopyter-0.3.2.data/data/share/jupyter/labextensions/neopyter/static/514.9ecfbc06ec3a6698fd1d.js.LICENSE.txt
neopyter-0.3.2.data/data/share/jupyter/labextensions/neopyter/static/524.d00fb55e6f85059944d3.js
neopyter-0.3.2.data/data/share/jupyter/labextensions/neopyter/static/635.67bf0a7b7b041a393f02.js
neopyter-0.3.2.dist-info/METADATA
neopyter-0.3.2.dist-info/WHEEL
neopyter-0.3.2.dist-info/licenses/LICENSE
neopyter-0.3.2.dist-info/RECORD
