Metadata-Version: 2.4
Name: neopyter
Version: 0.3.2
Dynamic: Keywords
Summary: A JupyterLab extension. Integrate JupyterLab and Neovim
Project-URL: Homepage, https://github.com/SUSTech-data/neopyter
Project-URL: Bug Tracker, https://github.com/SUSTech-data/neopyter/issues
Project-URL: Repository, https://github.com/SUSTech-data/neopyter
Author-email: Abao Zhang <abaodoit@gmail.com>
License: BSD 3-Clause License
License-File: LICENSE
Classifier: Framework :: Jupyter
Classifier: Framework :: Jupyter :: JupyterLab
Classifier: Framework :: Jupyter :: JupyterLab :: 4
Classifier: Framework :: Jupyter :: JupyterLab :: Extensions
Classifier: Framework :: Jupyter :: JupyterLab :: Extensions :: Prebuilt
Classifier: License :: OSI Approved :: BSD License
Classifier: Programming Language :: Python
Classifier: Programming Language :: Python :: 3
Classifier: Programming Language :: Python :: 3.6
Classifier: Programming Language :: Python :: 3.7
Classifier: Programming Language :: Python :: 3.8
Classifier: Programming Language :: Python :: 3.9
Classifier: Programming Language :: Python :: 3.10
Classifier: Programming Language :: Python :: 3.11
Requires-Python: >=3.8
Requires-Dist: jupyterlab<5,>=4.0.0
Provides-Extra: dev
Requires-Dist: coverage; extra == 'dev'
Requires-Dist: hatch; extra == 'dev'
Requires-Dist: hatch-nodejs-version; extra == 'dev'
Requires-Dist: pytest; extra == 'dev'
Requires-Dist: pytest-asyncio; extra == 'dev'
Requires-Dist: pytest-cov; extra == 'dev'
Requires-Dist: pytest-jupyter[server]>=0.6.0; extra == 'dev'
Requires-Dist: ruff; extra == 'dev'
